quantaq/__init__.py
quantaq/client.py
quantaq/endpoints/__init__.py
quantaq/endpoints/cellular/__init__.py
quantaq/endpoints/data/__init__.py
quantaq/endpoints/devices/__init__.py
quantaq/endpoints/logs/__init__.py
quantaq/endpoints/models/__init__.py
quantaq/endpoints/networks/__init__.py
quantaq/endpoints/organizations/__init__.py
quantaq/endpoints/users/__init__.py
quantaq/exceptions.py
quantaq/utils.py
py_quantaq-1.3.0.dist-info/LICENSE
py_quantaq-1.3.0.dist-info/METADATA
py_quantaq-1.3.0.dist-info/WHEEL
py_quantaq-1.3.0.dist-info/RECORD
