Metadata-Version: 2.1
Name: py-quantaq
Version: 1.3.0
Summary: API wrapper and utils for QuantAQ, Inc.
Home-page: https://quant-aq.github.io/py-quantaq
License: Apache-2.0
Author: David H Hagan
Author-email: david.hagan@quant-aq.com
Requires-Python: >=3.8,<3.11
Classifier: License :: OSI Approved :: Apache Software License
Classifier: Programming Language :: Python :: 3
Classifier: Programming Language :: Python :: 3.8
Classifier: Programming Language :: Python :: 3.9
Classifier: Programming Language :: Python :: 3.10
Requires-Dist: numpy (>=1.22)
Requires-Dist: pandas (>=1.0)
Requires-Dist: requests (>=2.24,<3.0)
Requires-Dist: setuptools (>=47.0,<70.0)
Requires-Dist: urllib3 (>=1.26.5)
Project-URL: Documentation, https://quant-aq.github.io/py-quantaq
Project-URL: Repository, https://github.com/quant-aq/py-quantaq
